[
  {
    "title": "컴포즈커피 메뉴 컴포즈 콤보 내 맘대로 조합 컴보",
    "link": "https://blog.naver.com/darkyoon85/223768900432",
    "description": "컴포즈 콤보 '컴보' 내 맘대로 조합하기 컴포즈커피 메뉴 컴포즈커피 메뉴 소개해 드릴게요. 출시 전부터 엄청 기대했던 컴포즈 콤보가 드디어 나왔어요! 음료와 토핑을 직접 조함해 만드는 새로운 스타일의... ",
    "bloggername": "다크윤의 맛집이야기♥",
    "postdate": "20250222"
  },
  {
    "title": "컴포즈커피 메뉴 리얼믹스커피 봄시즌 음료 추천",
    "link": "https://blog.naver.com/etienne03/223853650698",
    "description": "3.컴포즈커피 메뉴 한눈에 보이는 컴포즈 메뉴판이에요. 기본 아메리카노 핫은 1500원 아이스는 1800원, 라떼와 카푸치노는 2900원, 바닐라라떼와 카라멜마끼아또는 3300원 가성비 카페인데요. 스무디, 프라페... ",
    "bloggername": "Barbie's place",
    "postdate": "20250502"
  },
  {
    "title": "컴포즈커피 메뉴 벚꽃 팝콘과 함께하는 오렌지 사샷추인가 봄",
    "link": "https://blog.naver.com/yunt80/223833028412",
    "description": "컴포즈커피 메뉴 벚꽃 팝콘과 함께하는 오렌지 사샷추인가 봄 컴포즈커피 봄에 찾아온 메뉴 오렌지 사샷추인가 봄 만나고 왔어요. 음료만 주문을 해도 되지만 함께 나온 벚꽃 팝콘도 같이 먹었는데... ",
    "bloggername": "윤티와놀자",
    "postdate": "20250415"
  },
  {
    "title": "컴포즈커피 메뉴 가격 팥절미 밀크쉐이크 추천",
    "link": "https://blog.naver.com/alswl0224/223840119256",
    "description": "다음에는 저의 여름철 원픽, 아이스크림 판매 매장에서만 사 먹을 수 있는 맛도리 아이스크림라떼 후기 들고올게요 지금까지 컴포즈커피 메뉴 가격 칼로리 내돈내산 솔직 후기였습니다. #컴포즈메뉴 #컴포즈... ",
    "bloggername": "망디의먹로그",
    "postdate": "20250420"
  },
  {
    "title": "컴포즈커피 메뉴 가격 오렌지 사샷추 쿠폰 할인",
    "link": "https://blog.naver.com/dryjazz/223847961033",
    "description": "컴포즈커피 메뉴 가격 오렌지 사샷추 반갑습니다 맛별사이구요 4월 27일 주말 일요일 후식 음료 마시러 방문한 단골 카페 그 장소로 이동 해볼게요 1.길동중앙점 위치 및 영업 정보 대중교통 이용할땐 길동역... ",
    "bloggername": "맛감별 멋감별 코리아",
    "postdate": "20250428"
  },
  {
    "title": "컴포즈커피 메뉴 딸기 연유라떼 딸기치즈스무디 와플 쿠키 후기",
    "link": "https://blog.naver.com/gftravel/223326569297",
    "description": "컴포즈커피 메뉴로 국내산 제철 논산딸기를 사용한 신메뉴가 나왔다길래 설레는 마음으로 방문했어요.... 치즈 좋아한다면 무조건 맛봐야 할 컴포즈 메뉴. 휘핑크림과 딸기 조각도 올라와 있어서 비주얼도 정말... ",
    "bloggername": "여행을 일상으로, 여행을 쓰다",
    "postdate": "20240118"
  },
  {
    "title": "컴포즈커피 메뉴 가격 제주 선셋 리프레시 익숙한 슬러시 맛",
    "link": "https://blog.naver.com/kangsy0203/223482957974",
    "description": "만든 컴포즈 메뉴 제주 선셋 리프레시 마셔봐서요 시원한 슬러시 스타일 메뉴로 더운 날씨에 한잔 마시기 딱 좋았습니다 1. 위치 및 영업시간 위치 컴포즈커피 서울대입구역 1호점으로 서울대입구역 5번에서... ",
    "bloggername": "떵이의 오즈나라",
    "postdate": "20240618"
  },
  {
    "title": "컴포즈커피 메뉴 생딸기 모찌 밀크쉐이크 생딸기가나슈라떼... ",
    "link": "https://blog.naver.com/lovableje/223709774020",
    "description": "날이 추워 서둘러 매장으로 들어서니 이번 컴포즈커피 메뉴를 소개하는 홍보 포스터가 붙어 있더라고요. Awesome Berry Festa 제철 생딸기를 품은 향긋한 블렌디드 시즌 별로 호불호 없이 모두가 좋아할만한 음료가... ",
    "bloggername": "쯘이네 꽃 같은 하루",
    "postdate": "20241230"
  },
  {
    "title": "컴포즈커피 메뉴 베스트컴보 쫀득카노 추천, 디저트와 커피를... ",
    "link": "https://blog.naver.com/kyoonsun7/223795537273",
    "description": "com/notice/206225 #컴포즈커피 #컴포즈신메뉴 #컴포즈컴보 #컴포즈콤보 #베스트컴보 #내맘대로컴보 #쫀득카노 #쫀득쿠키 #컴포즈메뉴 #카페디저트 #커피추천 #컴포즈쫀득카노",
    "bloggername": "Hello, Delicious",
    "postdate": "20250314"
  },
  {
    "title": "컴포즈커피 콤보 신상 메뉴 추천 컴포즈 콤보 내돈내산 가격",
    "link": "https://blog.naver.com/yyy12393/223789757859",
    "description": "디저트 메뉴와 66가지의 음료의 조합이 가능한 콤보 컴포즈 메뉴 종류가 이렇게나 많았었나요? 콤보... 끝나가네요 #컴포즈커피 #컴포즈커피메뉴 #컴포즈콤보 #컴포즈콤보가격 #더블샷캬라멜팝콘... ",
    "bloggername": "얼레벌레 또 하루가 지나감!",
    "postdate": "20250309"
  },
  {
    "title": "컴포즈커피 메뉴 가격 신메뉴 딸기 연유라떼 추천",
    "link": "https://blog.naver.com/hong_flow/223326555843",
    "description": "띄더군요 #컴포즈 #컴포즈커피 #컴포즈메뉴 #컴포즈커피메뉴 마침 비도 추적추적 내리겠다 ? 잘 되었다 싶어 부랴부랴 매장 안으로 들어갔답니다 이에 대하여 간단하게 말하자면 일단 슬슬 봄 준비를 하는 걸까... ",
    "bloggername": "홍련화",
    "postdate": "20240118"
  },
  {
    "title": "컴포즈커피 메뉴 가격 최신ver. 신메뉴 레몬사샷추 묘하게 맛남",
    "link": "https://blog.naver.com/yuna_1024/223834057836",
    "description": "#컴포즈커피메뉴판 참고하셔요. 금액 변동이 조금씩 있지만 고정 메뉴들은 늘 그대로 자리를 지키고 있답니다. 이렇게 메뉴가 다양해도 늘 먹는 것만 먹긴 하지만요.. ? #컴포즈커피가격 잘보이도록 반씩... ",
    "bloggername": "날마다 좋은 날 ♥",
    "postdate": "20250415"
  },
  {
    "title": "컴포즈커피 메뉴 벚꽃 팝콘 콤보 레몬 사샷추인가 봄",
    "link": "https://blog.naver.com/darkyoon85/223844244188",
    "description": "컴포즈커피 메뉴 벚꽃 팝콘 콤보 레몬 사샷추인가 봄 벚꽃 팝콘 콤보 &amp; 레몬 사샷추인가 봄 컴포즈커피 메뉴 컴포즈커피 메뉴 소개해 드릴게요. 얼마 전 출시한 컴포즈 콤보! 봄 시즌을 맞아 벚꽃 팝콘 콤보... ",
    "bloggername": "다크윤의 맛집이야기♥",
    "postdate": "20250427"
  },
  {
    "title": "컴포즈커피 메뉴 쫀득쿠키 디저트 베스트컴보 가격 추천",
    "link": "https://blog.naver.com/ssso131/223776420070",
    "description": "컴포즈 커피는 가성비도 좋고 커피 맛도 좋아서 컴포즈커피 단골일 정도로 정말 자주 가는데 이번에 특별한 컴포즈커피 신메뉴 컴포즈 콤보를 맛보러 다녀왔습니다! 바로 리뷰 시작해 볼게요! 위치 제가... ",
    "bloggername": "먹으려고 운동하는 집사일기!",
    "postdate": "20250227"
  },
  {
    "title": "컴포즈커피 메뉴 컴포즈 콤보 쫀득쿠키 아아 조합 쫀득카노",
    "link": "https://blog.naver.com/etienne03/223770369117",
    "description": "컴포즈커피 메뉴 컴포즈 콤보 쫀득쿠키 아아 조합 쫀득카노 안녕하세요 바비에요 오늘은 컴포즈커피 메뉴 소식을 가져왔어요. 어제 롯데몰 갔다가 커피 한잔 마시려고 들어갔는데 신메뉴가 나왔더라고요.... ",
    "bloggername": "Barbie's place",
    "postdate": "20250223"
  },
  {
    "title": "컴포즈커피 메뉴 여름의 문턱에서 만나는 파인 선셋 스무디",
    "link": "https://blog.naver.com/yunt80/223854595670",
    "description": "컴포즈커피 메뉴 여름의 문턱에서 만나는 파인 선셋 스무디 컴포즈커피 여름이라 찾아온 3종의 메뉴가 있어서 다녀왔어요. 논산 수박 음료도 시원해 보여서 마시고 싶긴 했지만 저는 일단 파인 선셋 스무디... ",
    "bloggername": "윤티와놀자",
    "postdate": "20250504"
  },
  {
    "title": "컴포즈커피 메뉴 가격 오렌지 사샷추 벚꽃팝콘 추천",
    "link": "https://blog.naver.com/alswl0224/223821338337",
    "description": "음료, 디저트 세트 먹고 키링도 득템해 보세요 지금까지 컴포즈커피 메뉴 가격 오렌지 사샷추 벚꽃팝콘 추천 내돈내산 솔직 후기였습니다 #컴포즈커피 #사샷추 #컴포즈메뉴 #컴포즈사샷추 #컴포즈벚꽃팝콘",
    "bloggername": "망디의먹로그",
    "postdate": "20250403"
  },
  {
    "title": "컴포즈커피 메뉴 베스트 메뉴 추천까지",
    "link": "https://blog.naver.com/8570447/223267144533",
    "description": "입맛에 맞는 걸로 드시면 좋을 것 같네요 다음에는 새로 나온 음료도 먹어보고 다시 한번 후기를 전해드리도록 하겠습니다 ~~~ #컴포즈커피 #컴포즈메뉴 #컴포즈커피추천메뉴 #컴포즈추천메뉴 #컴포즈커피메뉴추천",
    "bloggername": "아라로그",
    "postdate": "20231117"
  },
  {
    "title": "컴포즈 신메뉴 12월 딸기 메뉴 가격, 국내산 딸기주스 리뷰",
    "link": "https://blog.naver.com/byonzee/223289059693",
    "description": "#컴포즈메뉴 #컴포즈신메뉴 #컴포즈커피 #컴포즈메뉴추천 #딸기라떼 #딸기주스 #논산딸기 #딸기치즈 #컴포즈커피메뉴 이 게시물은 컴포즈커피로부터 소정의 활동비와 제품을 제공받아 작성되었습니다. 그치만... ",
    "bloggername": "❤️사하 XAHA❤️",
    "postdate": "20231211"
  },
  {
    "title": "컴포즈커피 메뉴 가격 아메리카노 커피콩빵 제로 리얼믹스커피... ",
    "link": "https://blog.naver.com/kangsy0203/223851503170",
    "description": "그래서 집에 들어오는 길에 컴포즈커피 메뉴 커피엔 역시 커피빵 테이크아웃해서 가볍게 즐겨봤답니다 아이스 아메리카노, 빵 조합이라서 무난하게 즐기기 좋았던 후기 지금부터 보여드릴게요~! 1. 위치 및... ",
    "bloggername": "떵이의 오즈나라",
    "postdate": "20250430"
  }
]